eerie/__init__.py
eerie/decoder.py
eerie/encoder.py
eerie/py.typed
eerie-0.0.1.dist-info/METADATA
eerie-0.0.1.dist-info/WHEEL
eerie-0.0.1.dist-info/RECORD
