Metadata-Version: 2.1
Name: Eerie
Version: 0.0.1
Summary: A sensible query string library for python.
Author: Daniel Knell
Author-email: contact@danielknell.co.uk
Requires-Python: >=3.10,<4.0
Classifier: Programming Language :: Python :: 3
Classifier: Programming Language :: Python :: 3.10
Classifier: Programming Language :: Python :: 3.11
